[
  {
    "TT": 1,
    "Môn": "Toán",
    "Chủ đề": "2. Số thập phân",
    "Bài/Nội dung": "Bài 10: Khái niệm số thập phân",
    "YCCĐ": "Nhận biết, đọc, viết số thập phân; cấu tạo hàng.",
    "Số tiết": 3,
    "Block": 1,
    "Tỉ lệ (%)": 0,
    "Số điểm cần đạt": 0,
    "Tổng số câu/ý": 4,
    "Điểm từng bài": 0,
    "Trắc nghiệm nhiều lựa chọn|Biết": 2,
    "Trắc nghiệm nhiều lựa chọn|Hiểu": 0,
    "Trắc nghiệm nhiều lựa chọn|VD": 0,
    "Đúng/Sai|Biết": 0,
    "Đúng/Sai|Hiểu": 1,
    "Đúng/Sai|VD": 0,
    "Nối cột|Biết": 0,
    "Nối cột|Hiểu": 0,
    "Nối cột|VD": 0,
    "Điền khuyết|Biết": 0,
    "Điền khuyết|Hiểu": 0,
    "Điền khuyết|VD": 0,
    "Tự luận|Biết": 0,
    "Tự luận|Hiểu": 0,
    "Tự luận|VD": 1
  },
  {
    "TT": 2,
    "Môn": "TV",
    "Chủ đề": "Chủ điểm 1",
    "Bài/Nội dung": "Bài 1",
    "YCCĐ": "Đọc hiểu văn bản, trả lời câu hỏi.",
    "Số tiết": 2,
    "Block": 1,
    "Tỉ lệ (%)": 0,
    "Số điểm cần đạt": 0,
    "Tổng số câu/ý": 2,
    "Điểm từng bài": 0,
    "Trắc nghiệm nhiều lựa chọn|Biết": 1,
    "Trắc nghiệm nhiều lựa chọn|Hiểu": 0,
    "Trắc nghiệm nhiều lựa chọn|VD": 0,
    "Đúng/Sai|Biết": 0,
    "Đúng/Sai|Hiểu": 0,
    "Đúng/Sai|VD": 0,
    "Nối cột|Biết": 0,
    "Nối cột|Hiểu": 0,
    "Nối cột|VD": 0,
    "Điền khuyết|Biết": 0,
    "Điền khuyết|Hiểu": 1,
    "Điền khuyết|VD": 0,
    "Tự luận|Biết": 0,
    "Tự luận|Hiểu": 0,
    "Tự luận|VD": 0
  }
]